profile_zoominfo_graphql_imp_local_python_package/ZoomInfo.py
profile_zoominfo_graphql_imp_local_python_package/__init__.py
profile_zoominfo_graphql_imp_local_python_package-0.0.5.dist-info/METADATA
profile_zoominfo_graphql_imp_local_python_package-0.0.5.dist-info/WHEEL
profile_zoominfo_graphql_imp_local_python_package-0.0.5.dist-info/top_level.txt
profile_zoominfo_graphql_imp_local_python_package-0.0.5.dist-info/RECORD
