Metadata-Version: 2.1
Name: profile-zoominfo-graphql-imp-local-python-package
Version: 0.0.5
Home-page: https://github.com/circles-zone/profile-zoominfo-graphql-imp-local-python-package
Author: Circles
Author-email: sahar.g@circ.zone
Classifier: Programming Language :: Python :: 3
Classifier: License :: Other/Proprietary License
Classifier: Operating System :: OS Independent
Requires-Dist: pytest >=7.4.0
Requires-Dist: python-dotenv >=1.0.0
Requires-Dist: database-without-orm-local >=0.0.104
Requires-Dist: logger-local >=0.0.66
Requires-Dist: profile-local >=0.0.34
Requires-Dist: zoomus >=1.2.1
